{"Nodes":[],"ExecutionTime":"2023-04-28T15:08:41.3927570Z","GenerationTime":"0001-01-01T00:00:00","PluginUserSpecFlowId":"b976c17d-ebf9-4830-ac33-60937767b641","CLIUserSpecFlowId":null,"ExecutionResults":[{"ContextType":"Scenario","FeatureFolderPath":"Features","FeatureTitle":"Order calculation","ScenarioTitle":"Add two numbers","ScenarioArguments":[],"Status":"TestError","StepResults":[{"Duration":"00:00:00.0038267","Status":"OK","Error":null,"Outputs":null},{"Duration":"00:00:00.0037676","Status":"TestError","Error":"Assert.Equals should not be used. Use Assert.AreEqual instead.","Outputs":null}],"Outputs":null}],"StepReports":null}